field-generator/Slope.py
field_generator/__init__.py
field_generator-0.2.1.dist-info/LICENSE
field_generator-0.2.1.dist-info/METADATA
field_generator-0.2.1.dist-info/WHEEL
field_generator-0.2.1.dist-info/top_level.txt
field_generator-0.2.1.dist-info/RECORD
