Metadata-Version: 2.1
Name: field-generator
Version: 0.2.1
Summary: A simple slope field generator
Home-page: https://github.com/iamawestruck/Slope-Field-Generator
Author: EQIKE
Author-email: lc20-0098@lclark.edu
License: MIT
Platform: UNKNOWN
Requires-Python: >=3.8
License-File: LICENSE
Requires-Dist: matplotlib
Requires-Dist: scipy
